sqllineage/__init__.py
sqllineage/cli.py
sqllineage/config.py
sqllineage/drawing.py
sqllineage/exceptions.py
sqllineage/io.py
sqllineage/runner.py
sqllineage/build/favicon.ico
sqllineage/build/index.html
sqllineage/build/assets/index-CAC0baxl.js
sqllineage/build/assets/index-D4gAWuuQ.css
sqllineage/core/__init__.py
sqllineage/core/analyzer.py
sqllineage/core/holders.py
sqllineage/core/metadata_provider.py
sqllineage/core/models.py
sqllineage/core/metadata/__init__.py
sqllineage/core/metadata/dummy.py
sqllineage/core/metadata/sqlalchemy.py
sqllineage/core/parser/__init__.py
sqllineage/core/parser/sqlfluff/__init__.py
sqllineage/core/parser/sqlfluff/analyzer.py
sqllineage/core/parser/sqlfluff/models.py
sqllineage/core/parser/sqlfluff/utils.py
sqllineage/core/parser/sqlfluff/extractors/__init__.py
sqllineage/core/parser/sqlfluff/extractors/base.py
sqllineage/core/parser/sqlfluff/extractors/copy.py
sqllineage/core/parser/sqlfluff/extractors/create_insert.py
sqllineage/core/parser/sqlfluff/extractors/cte.py
sqllineage/core/parser/sqlfluff/extractors/drop.py
sqllineage/core/parser/sqlfluff/extractors/merge.py
sqllineage/core/parser/sqlfluff/extractors/noop.py
sqllineage/core/parser/sqlfluff/extractors/rename.py
sqllineage/core/parser/sqlfluff/extractors/select.py
sqllineage/core/parser/sqlfluff/extractors/unload.py
sqllineage/core/parser/sqlfluff/extractors/update.py
sqllineage/core/parser/sqlparse/__init__.py
sqllineage/core/parser/sqlparse/analyzer.py
sqllineage/core/parser/sqlparse/models.py
sqllineage/core/parser/sqlparse/utils.py
sqllineage/core/parser/sqlparse/handlers/__init__.py
sqllineage/core/parser/sqlparse/handlers/base.py
sqllineage/core/parser/sqlparse/handlers/cte.py
sqllineage/core/parser/sqlparse/handlers/source.py
sqllineage/core/parser/sqlparse/handlers/swap_partition.py
sqllineage/core/parser/sqlparse/handlers/target.py
sqllineage/data/tpcds/query01.sql
sqllineage/data/tpcds/query02.sql
sqllineage/data/tpcds/query03.sql
sqllineage-1.5.6.dist-info/METADATA
sqllineage-1.5.6.dist-info/WHEEL
sqllineage-1.5.6.dist-info/entry_points.txt
sqllineage-1.5.6.dist-info/licenses/LICENSE
sqllineage-1.5.6.dist-info/RECORD
