Metadata-Version: 2.4
Name: sqllineage
Version: 1.5.6
Summary: SQL Lineage Analysis Tool powered by Python
Project-URL: Homepage, https://reata.github.io/sqllineage/
Project-URL: Documentation, https://sqllineage.readthedocs.io/en/latest/
Project-URL: Repository, https://github.com/reata/sqllineage.git
Project-URL: Issues, https://github.com/reata/sqllineage/issues
Project-URL: Changelog, https://github.com/reata/sqllineage/releases
Author-email: Reata <reddevil.hjw@gmail.com>
Maintainer-email: Reata <reddevil.hjw@gmail.com>
License-Expression: MIT
License-File: LICENSE
Keywords: data-discovery,data-governance,data-lineage,lineage,metadata,sql
Classifier: Development Status :: 5 - Production/Stable
Classifier: Operating System :: OS Independent
Classifier: Programming Language :: Python :: 3
Classifier: Programming Language :: Python :: 3.9
Classifier: Programming Language :: Python :: 3.10
Classifier: Programming Language :: Python :: 3.11
Classifier: Programming Language :: Python :: 3.12
Classifier: Programming Language :: Python :: 3.13
Classifier: Programming Language :: Python :: Implementation :: CPython
Requires-Python: >=3.9
Requires-Dist: networkx>=2.4
Requires-Dist: sqlalchemy>=2.0.0
Requires-Dist: sqlfluff>=3.2.0
Requires-Dist: sqlparse>=0.5.0
Provides-Extra: ci
Requires-Dist: black>=25.1.0; extra == 'ci'
Requires-Dist: mypy>=1.17.1; extra == 'ci'
Requires-Dist: pytest-cov>=6.2.1; extra == 'ci'
Requires-Dist: pytest>=8.4.1; extra == 'ci'
Requires-Dist: ruff>=0.12.10; extra == 'ci'
Requires-Dist: tox>=4.28.4; extra == 'ci'
Requires-Dist: twine>=6.1.0; extra == 'ci'
Requires-Dist: wheel>=0.45.1; extra == 'ci'
Provides-Extra: docs
Requires-Dist: sphinx-rtd-theme>=0.5.0; extra == 'docs'
Requires-Dist: sphinx>=3.2.0; extra == 'docs'
